{
  "original_question": "In an arithmetic sequence $\\{a_n\\}$, let $S_n$ denote the sum of the first $n$ terms. Given that $\\frac {a_{2}}{a_{3}}= \\frac {1}{3}$, find the value of $\\frac {S_{4}}{S_{5}}$.\n\nPresent the answer in LaTex format: \\boxed{Your answer}",
  "num_entries": 6,
  "entries": [
    {
      "dataset": "numina_cn_k12",
      "original_question_id": 0,
      "type": "similar",
      "id": 2,
      "original_incomplete_question": "In an arithmetic sequence \\{a_n\\}, let S_n denote the sum of the first n terms. Given that \\frac {a_{1}}{a_{2}}= [BLANK], find the value of \\frac {S_{3}}{S_{4}}.",
      "variants": [
        {
          "id": 1,
          "variant": "In a sequence defined by arithmetic progression \\{a_n\\}, let S_n represent the total of the initial n terms. Knowing that \\frac {a_{1}}{a_{2}}= [BLANK], determine the value of \\frac {S_{3}}{S_{4}}.",
          "strategy": "mixed_fallback"
        },
        {
          "id": 2,
          "variant": "In a sequence defined by arithmetic progression \\{a_n\\}, let S_n represent the sum of the initial n terms. It is given that \\frac {a_{1}}{a_{2}}= [BLANK], determine the value of \\frac {S_{3}}{S_{4}}.",
          "strategy": "mixed_fallback"
        },
        {
          "id": 3,
          "variant": ". In an arithmetic sequence \\{a_n\\}, let S_n denote the sum of the first n termsGiven that \\frac {a_{1}}{a_{2}}= [BLANK], find the value of \\frac {S_{3}}{S_{4}}.",
          "strategy": "mixed_fallback"
        },
        {
          "id": 4,
          "variant": "In a sequence defined by arithmetic progression \\{a_n\\}, let S_n represent the total of the initial n terms. If it is known that \\frac {a_{1}}{a_{2}}= [BLANK], determine the value of \\frac {S_{3}}{S_{4}}.",
          "strategy": "mixed_fallback"
        },
        {
          "id": 5,
          "variant": "In an arithmetic series \\{a_n\\}, let S_n represent the total of the initial n terms. Knowing that \\frac {a_{1}}{a_{2}}= [BLANK], determine the value of \\frac {S_{3}}{S_{4}}.",
          "strategy": "mixed_fallback"
        }
      ]
    },
    {
      "dataset": "numina_cn_k12",
      "original_question_id": 0,
      "type": "similar",
      "id": 3,
      "original_incomplete_question": "In an arithmetic sequence \\{a_n\\}, let S_n denote the sum of the first n terms. Given that \\frac {a_{4}}{a_{5}}= [BLANK], find the value of \\frac {S_{6}}{S_{7}}.",
      "variants": [
        {
          "id": 1,
          "variant": "In a sequence defined by arithmetic progression \\{a_n\\}, let S_n represent the total of the initial n terms. Knowing that \\frac {a_{4}}{a_{5}}= [BLANK], determine the value of \\frac {S_{6}}{S_{7}}.",
          "strategy": "mixed_fallback"
        },
        {
          "id": 2,
          "variant": "In an arithmetic sequence \\{a_n\\}, let S_n represent the total of the initial n terms. Knowing that \\frac {a_{4}}{a_{5}}= [BLANK], determine the value of \\frac {S_{6}}{S_{7}}.",
          "strategy": "mixed_fallback"
        },
        {
          "id": 3,
          "variant": ". In an arithmetic sequence \\{a_n\\}, let S_n denote the sum of the first n termsGiven that \\frac {a_{4}}{a_{5}}= [BLANK], find the value of \\frac {S_{6}}{S_{7}}.",
          "strategy": "mixed_fallback"
        },
        {
          "id": 4,
          "variant": "In a sequence defined by arithmetic progression \\{a_n\\}, let S_n represent the total of the initial n terms. If it is known that \\frac {a_{4}}{a_{5}}= [BLANK], determine the value of \\frac {S_{6}}{S_{7}}.",
          "strategy": "mixed_fallback"
        },
        {
          "id": 5,
          "variant": "In a sequence defined by arithmetic progression \\{a_n\\}, let S_n represent the total of the initial n terms. It is provided that \\frac {a_{4}}{a_{5}}= [BLANK], determine the value of \\frac {S_{6}}{S_{7}}.",
          "strategy": "mixed_fallback"
        }
      ]
    },
    {
      "dataset": "numina_cn_k12",
      "original_question_id": 0,
      "type": "similar",
      "id": 4,
      "original_incomplete_question": "In an arithmetic sequence \\{a_n\\}, let S_n denote the sum of the first n terms. Given that \\frac {a_{5}}{a_{6}}= [BLANK], find the value of \\frac {S_{7}}{S_{8}}.",
      "variants": [
        {
          "id": 1,
          "variant": "In a sequence of numbers defined by arithmetic progression \\{a_n\\}, let S_n represent the total of the initial n terms. Knowing that \\frac {a_{5}}{a_{6}}= [BLANK], determine the value of \\frac {S_{7}}{S_{8}}.",
          "strategy": "mixed_fallback"
        },
        {
          "id": 2,
          "variant": "In an arithmetic series \\{a_n\\}, let S_n represent the total of the initial n terms. It is known that \\frac {a_{5}}{a_{6}}= [BLANK], determine the value of \\frac {S_{7}}{S_{8}}.",
          "strategy": "mixed_fallback"
        },
        {
          "id": 3,
          "variant": ". In an arithmetic sequence \\{a_n\\}, let S_n denote the sum of the first n termsGiven that \\frac {a_{5}}{a_{6}}= [BLANK], find the value of \\frac {S_{7}}{S_{8}}.",
          "strategy": "mixed_fallback"
        },
        {
          "id": 4,
          "variant": "In an arithmetic progression \\{a_n\\}, let S_n represent the total of the initial n terms. Knowing that \\frac {a_{5}}{a_{6}}= [BLANK], determine the value of \\frac {S_{7}}{S_{8}}.",
          "strategy": "mixed_fallback"
        },
        {
          "id": 5,
          "variant": "In a sequence defined by arithmetic progression \\{a_n\\}, let S_n represent the total of the initial n terms. It is known that \\frac {a_{5}}{a_{6}}= [BLANK], determine the value of \\frac {S_{7}}{S_{8}}.",
          "strategy": "mixed_fallback"
        }
      ]
    },
    {
      "dataset": "numina_cn_k12",
      "original_question_id": 0,
      "type": "similar",
      "id": 1,
      "original_incomplete_question": "In an arithmetic sequence \\{a_n\\}, let S_n denote the sum of the first n terms. Given that \\frac {a_{3}}{a_{4}}= [BLANK], find the value of \\frac {S_{5}}{S_{6}}.",
      "variants": [
        {
          "id": 1,
          "variant": "In a sequence defined by arithmetic progression \\{a_n\\}, let S_n represent the total of the initial n terms. Knowing that \\frac {a_{3}}{a_{4}}= [BLANK], determine the value of \\frac {S_{5}}{S_{6}}.",
          "strategy": "mixed_fallback"
        },
        {
          "id": 2,
          "variant": "In a sequence defined by arithmetic progression \\{a_n\\}, let S_n represent the total of the initial n terms. It is known that \\frac {a_{3}}{a_{4}}= [BLANK], determine the value of \\frac {S_{5}}{S_{6}}.",
          "strategy": "mixed_fallback"
        },
        {
          "id": 3,
          "variant": ". In an arithmetic sequence \\{a_n\\}, let S_n denote the sum of the first n termsGiven that \\frac {a_{3}}{a_{4}}= [BLANK], find the value of \\frac {S_{5}}{S_{6}}.",
          "strategy": "mixed_fallback"
        },
        {
          "id": 4,
          "variant": "In an arithmetic sequence \\{a_n\\}, let S_n represent the sum of the initial n terms. Given that \\frac {a_{3}}{a_{4}}= [BLANK], determine the value of \\frac {S_{5}}{S_{6}}.",
          "strategy": "mixed_fallback"
        },
        {
          "id": 5,
          "variant": "In a sequence defined by arithmetic progression \\{a_n\\}, let S_n represent the total of the first n elements. Knowing that \\frac {a_{3}}{a_{4}}= [BLANK], determine the value of \\frac {S_{5}}{S_{6}}.",
          "strategy": "mixed_fallback"
        }
      ]
    },
    {
      "dataset": "numina_cn_k12",
      "original_question_id": 0,
      "type": "similar",
      "id": 5,
      "original_incomplete_question": "In an arithmetic sequence \\{a_n\\}, let S_n denote the sum of the first n terms. Given that \\frac {a_{2}}{a_{4}}= [BLANK], find the value of \\frac {S_{4}}{S_{5}}.",
      "variants": [
        {
          "id": 1,
          "variant": "In an arithmetic progression \\{a_n\\}, let S_n represent the total of the first n terms. If \\frac {a_{2}}{a_{4}}= [BLANK], determine the value of \\frac {S_{4}}{S_{5}}.",
          "strategy": "mixed_fallback"
        },
        {
          "id": 2,
          "variant": "In an arithmetic sequence \\{a_n\\}, let S_n represent the total of the initial n terms. It is given that \\frac {a_{2}}{a_{4}}= [BLANK], determine the value of \\frac {S_{4}}{S_{5}}.",
          "strategy": "mixed_fallback"
        },
        {
          "id": 3,
          "variant": ". In an arithmetic sequence \\{a_n\\}, let S_n denote the sum of the first n termsGiven that \\frac {a_{2}}{a_{4}}= [BLANK], find the value of \\frac {S_{4}}{S_{5}}.",
          "strategy": "mixed_fallback"
        },
        {
          "id": 4,
          "variant": "In an arithmetic series \\{a_n\\}, let S_n represent the total of the initial n terms. It is known that \\frac {a_{2}}{a_{4}}= [BLANK], determine the value of \\frac {S_{4}}{S_{5}}.",
          "strategy": "mixed_fallback"
        },
        {
          "id": 5,
          "variant": "In a sequence defined by arithmetic progression \\{a_n\\}, let S_n represent the total of the first n terms. Given that \\frac {a_{2}}{a_{4}}= [BLANK], determine the value of \\frac {S_{4}}{S_{5}}.",
          "strategy": "mixed_fallback"
        }
      ]
    },
    {
      "dataset": "numina_cn_k12",
      "original_question_id": 0,
      "type": "original",
      "id": 0,
      "original_incomplete_question": "In an arithmetic sequence $\\{a_n\\}$, let $S_n$ denote the sum of the first $n$ terms. Given that $\\frac {a_{2}}{a_{3}}= [BLANK]$, find the value of $\\frac {S_{4}}{S_{5}}$.",
      "variants": [
        {
          "id": 1,
          "variant": "In an arithmetic progression $\\{a_n\\}$, let $S_n$ represent the total of the initial $n$ terms. It is known that $\\frac {a_{2}}{a_{3}}= [BLANK]$, determine the value of $\\frac {S_{4}}{S_{5}}$.",
          "strategy": "mixed_fallback"
        },
        {
          "id": 2,
          "variant": "In an arithmetic progression $\\{a_n\\}$, let $S_n$ represent the total of the initial $n$ terms. If it is known that $\\frac {a_{2}}{a_{3}}= [BLANK]$, determine the value of $\\frac {S_{4}}{S_{5}}$.",
          "strategy": "mixed_fallback"
        },
        {
          "id": 3,
          "variant": ". In an arithmetic sequence $\\{a_n\\}$, let $S_n$ denote the sum of the first $n$ termsGiven that $\\frac {a_{2}}{a_{3}}= [BLANK]$, find the value of $\\frac {S_{4}}{S_{5}}$.",
          "strategy": "mixed_fallback"
        },
        {
          "id": 4,
          "variant": "In an arithmetic progression $\\{a_n\\}$, let $S_n$ represent the total of the initial $n$ terms. Knowing that $\\frac {a_{2}}{a_{3}}= [BLANK]$, determine the value of $\\frac {S_{4}}{S_{5}}$.",
          "strategy": "mixed_fallback"
        },
        {
          "id": 5,
          "variant": "In a sequence defined by arithmetic progression $\\{a_n\\}$, let $S_n$ represent the total of the initial $n$ terms. It is known that $\\frac {a_{2}}{a_{3}}= [BLANK]$, determine the value of $\\frac {S_{4}}{S_{5}}$.",
          "strategy": "mixed_fallback"
        }
      ]
    }
  ]
}