{
  "original_question": "Calculate the difference between the sums of two sequences:\n$(2001 + 2002 + 2003 + \\cdots + 2093) - (301 + 302 + 303 + \\cdots + 393) = ?$\nA) 150,000\nB) 157,100\nC) 158,100\nD) 160,000\nE) 180,000\n\nPresent the answer in LaTex format: \\boxed{Your answer}",
  "info_removed_type": "the specific range of numbers in sequences",
  "num_pairs": 6,
  "pairs": [
    {
      "dataset": "numina_synthetic_amc",
      "original_question_id": 0,
      "similar_question_id": null,
      "type": "original",
      "original_question": "Calculate the difference between the sums of two sequences:\n$(2001 + 2002 + 2003 + \\cdots + 2093) - (301 + 302 + 303 + \\cdots + 393) = ?$\nA) 150,000\nB) 157,100\nC) 158,100\nD) 160,000\nE) 180,000\n\nPresent the answer in LaTex format: \\boxed{Your answer}",
      "incomplete_question": "Calculate the difference between the sums of two sequences: $([BLANK] + [BLANK] + [BLANK] + \\cdots + [BLANK]) - ([BLANK] + [BLANK] + [BLANK] + \\cdots + [BLANK]) = ?$ A) 150,000 B) 157,100 C) 158,100 D) 160,000 E) 180,000",
      "info_removed": "the specific range of numbers in sequences"
    },
    {
      "dataset": "numina_synthetic_amc",
      "original_question_id": 0,
      "similar_question_id": 1,
      "type": "similar",
      "original_question": "(3001 + 3002 + 3003 + \\cdots + 3093) - (401 + 402 + 403 + \\cdots + 493) = ?",
      "incomplete_question": "([BLANK] + [BLANK] + [BLANK] + \\cdots + [BLANK]) - ([BLANK] + [BLANK] + [BLANK] + \\cdots + [BLANK]) = ?",
      "info_removed": "the specific range of numbers in sequences"
    },
    {
      "dataset": "numina_synthetic_amc",
      "original_question_id": 0,
      "similar_question_id": 2,
      "type": "similar",
      "original_question": "(4001 + 4002 + 4003 + \\cdots + 4093) - (501 + 502 + 503 + \\cdots + 593) = ?",
      "incomplete_question": "([BLANK] + [BLANK] + [BLANK] + \\cdots + [BLANK]) - ([BLANK] + [BLANK] + [BLANK] + \\cdots + [BLANK]) = ?",
      "info_removed": "the specific range of numbers in sequences"
    },
    {
      "dataset": "numina_synthetic_amc",
      "original_question_id": 0,
      "similar_question_id": 3,
      "type": "similar",
      "original_question": "(5001 + 5002 + 5003 + \\cdots + 5093) - (601 + 602 + 603 + \\cdots + 693) = ?",
      "incomplete_question": "([BLANK] + [BLANK] + [BLANK] + \\cdots + [BLANK]) - ([BLANK] + [BLANK] + [BLANK] + \\cdots + [BLANK]) = ?",
      "info_removed": "the specific range of numbers in sequences"
    },
    {
      "dataset": "numina_synthetic_amc",
      "original_question_id": 0,
      "similar_question_id": 4,
      "type": "similar",
      "original_question": "(6001 + 6002 + 6003 + \\cdots + 6093) - (701 + 702 + 703 + \\cdots + 793) = ?",
      "incomplete_question": "([BLANK] + [BLANK] + [BLANK] + \\cdots + [BLANK]) - ([BLANK] + [BLANK] + [BLANK] + \\cdots + [BLANK]) = ?",
      "info_removed": "the specific range of numbers in sequences"
    },
    {
      "dataset": "numina_synthetic_amc",
      "original_question_id": 0,
      "similar_question_id": 5,
      "type": "similar",
      "original_question": "(7001 + 7002 + 7003 + \\cdots + 7093) - (801 + 802 + 803 + \\cdots + 893) = ?",
      "incomplete_question": "([BLANK] + [BLANK] + [BLANK] + \\cdots + [BLANK]) - ([BLANK] + [BLANK] + [BLANK] + \\cdots + [BLANK]) = ?",
      "info_removed": "the specific range of numbers in sequences"
    }
  ],
  "num_valid_similars": 5
}